pytest_splunk_addon_ui_smartx/__init__.py
pytest_splunk_addon_ui_smartx/alert_actions/__init__.py
pytest_splunk_addon_ui_smartx/alert_actions/components/__init__.py
pytest_splunk_addon_ui_smartx/alert_actions/components/account_select.py
pytest_splunk_addon_ui_smartx/alert_actions/components/action_controls.py
pytest_splunk_addon_ui_smartx/alert_actions/components/alert_base_component.py
pytest_splunk_addon_ui_smartx/alert_actions/components/alert_base_control.py
pytest_splunk_addon_ui_smartx/alert_actions/components/button.py
pytest_splunk_addon_ui_smartx/alert_actions/components/checkbox.py
pytest_splunk_addon_ui_smartx/alert_actions/components/dropdown.py
pytest_splunk_addon_ui_smartx/alert_actions/components/searchbox.py
pytest_splunk_addon_ui_smartx/alert_actions/components/single_select.py
pytest_splunk_addon_ui_smartx/alert_actions/components/table.py
pytest_splunk_addon_ui_smartx/alert_actions/components/textbox.py
pytest_splunk_addon_ui_smartx/alert_actions/components/toggle.py
pytest_splunk_addon_ui_smartx/backend_confs.py
pytest_splunk_addon_ui_smartx/base_test.py
pytest_splunk_addon_ui_smartx/components/__init__.py
pytest_splunk_addon_ui_smartx/components/base_component.py
pytest_splunk_addon_ui_smartx/components/conf_table.py
pytest_splunk_addon_ui_smartx/components/controls/__init__.py
pytest_splunk_addon_ui_smartx/components/controls/base_control.py
pytest_splunk_addon_ui_smartx/components/controls/button.py
pytest_splunk_addon_ui_smartx/components/controls/checkbox.py
pytest_splunk_addon_ui_smartx/components/controls/checkboxgroup.py
pytest_splunk_addon_ui_smartx/components/controls/file.py
pytest_splunk_addon_ui_smartx/components/controls/learn_more.py
pytest_splunk_addon_ui_smartx/components/controls/message.py
pytest_splunk_addon_ui_smartx/components/controls/multi_select.py
pytest_splunk_addon_ui_smartx/components/controls/oauth_select.py
pytest_splunk_addon_ui_smartx/components/controls/single_select.py
pytest_splunk_addon_ui_smartx-5.4.0.dist-info/LICENSE
pytest_splunk_addon_ui_smartx-5.4.0.dist-info/METADATA
pytest_splunk_addon_ui_smartx-5.4.0.dist-info/WHEEL
pytest_splunk_addon_ui_smartx-5.4.0.dist-info/entry_points.txt
pytest_splunk_addon_ui_smartx-5.4.0.dist-info/RECORD
