Metadata-Version: 2.1
Name: pytest-splunk-addon-ui-smartx
Version: 5.4.0
Summary: Library to support testing Splunk Add-on UX
License: Apache-2.0
Author: Splunk
Author-email: addonfactory@splunk.com
Requires-Python: >=3.7,<4.0
Classifier: Framework :: Pytest
Classifier: Intended Audience :: Developers
Classifier: License :: OSI Approved :: Apache Software License
Classifier: Operating System :: OS Independent
Classifier: Programming Language :: Python
Classifier: Programming Language :: Python :: 3
Classifier: Programming Language :: Python :: 3.7
Classifier: Programming Language :: Python :: 3.8
Classifier: Programming Language :: Python :: 3.9
Classifier: Programming Language :: Python :: 3.10
Classifier: Programming Language :: Python :: 3.11
Classifier: Programming Language :: Python :: 3.12
Classifier: Programming Language :: Python :: 3.13
Classifier: Topic :: Software Development :: Testing
Requires-Dist: cssselect
Requires-Dist: lxml (>=5.1.0,<6.0.0)
Requires-Dist: msedge-selenium-tools
Requires-Dist: pytest-html
Requires-Dist: pytest-splunk-addon (>=6.0.0,<7.0.0)
Requires-Dist: selenium
Requires-Dist: urllib3 (>=1.21.1,<2.0.0)
Requires-Dist: webdriver-manager
